hospinet/__init__.py
hospinet/cleaner.py
hospinet/overlap_fixer.py
hospinet/temporal_network.py
hospinet-1.0.2.dist-info/LICENSE
hospinet-1.0.2.dist-info/METADATA
hospinet-1.0.2.dist-info/WHEEL
hospinet-1.0.2.dist-info/top_level.txt
hospinet-1.0.2.dist-info/RECORD
