Metadata-Version: 2.1
Name: hospinet
Version: 1.0.2
Summary: Temporal Networks of Hospitals Using Patient Transfers
Author-email: David Wu <david.wu1@monash.edu>
License: Copyright (c) 2024 hospinet authors
Project-URL: Homepage, https://github.com/dwu0042/hospinet
Project-URL: Issues, https://github.com/dwu0042/hospinet/issues
Classifier: License :: OSI Approved :: MIT License
Classifier: Programming Language :: Python :: 3
Classifier: Operating System :: OS Independent
Requires-Python: >=3.11
License-File: LICENSE
Requires-Dist: numpy>=1.19.0
Requires-Dist: polars>=1.0
Requires-Dist: networkx>=3
Provides-Extra: dev
Requires-Dist: pytest; extra == "dev"
Provides-Extra: docs
Requires-Dist: pdoc3; extra == "docs"
Provides-Extra: vignette
Requires-Dist: matplotlib>=3.6; extra == "vignette"
